Metadata-Version: 2.1
Name: ohikendoit-stats-toolkit
Version: 0.1.0
Summary: Gaussian and Binomial distributions
Home-page: UNKNOWN
Author: Yoonseong Jung
Author-email: ohikendoit@gmail.com
License: UNKNOWN
Platform: UNKNOWN
